pyBIA/__init__.py
pyBIA/catalog.py
pyBIA/cnn_model.py
pyBIA/data_augmentation.py
pyBIA/data_processing.py
pyBIA/ensemble_model.py
pyBIA/feature_selection.py
pyBIA/image_moments.py
pyBIA/optimization.py
pyBIA/outlier_detection.py
pybia-1.51.dist-info/licenses/LICENSE
pybia-1.51.dist-info/METADATA
pybia-1.51.dist-info/WHEEL
pybia-1.51.dist-info/top_level.txt
pybia-1.51.dist-info/RECORD
