Metadata-Version: 2.4
Name: pyBIA
Version: 1.51
Summary: Machine learning-based framework for Lyalpha Blob Detection
Home-page: https://github.com/Professor-G/pyBIA
Author: Daniel Godines
Author-email: danielgodinez123@gmail.com
License: GPL-3.0
Classifier: Development Status :: 5 - Production/Stable
Classifier: Intended Audience :: Science/Research
Classifier: Topic :: Scientific/Engineering :: Astronomy
Classifier: License :: OSI Approved :: GNU General Public License v3 (GPLv3)
Classifier: Programming Language :: Python :: 3
Classifier: Programming Language :: Python :: 3.12
Classifier: Operating System :: OS Independent
Requires-Python: >=3.12
License-File: LICENSE
Requires-Dist: numpy==2.1.3
Requires-Dist: pandas==2.3.1
Requires-Dist: matplotlib==3.10.3
Requires-Dist: astropy==7.1.0
Requires-Dist: photutils==2.2.0
Requires-Dist: scipy==1.16.0
Requires-Dist: tensorflow==2.19.0
Requires-Dist: progress==1.6.1
Requires-Dist: joblib==1.5.1
Requires-Dist: scikit-learn==1.7.1
Requires-Dist: xgboost==3.0.2
Requires-Dist: optuna==4.4.0
Requires-Dist: optuna-integration==4.4.0
Requires-Dist: shap==0.48.0
Requires-Dist: tqdm==4.67.1
Requires-Dist: scikit-image==0.25.2
Requires-Dist: PyWavelets==1.8.0
Dynamic: author
Dynamic: author-email
Dynamic: classifier
Dynamic: description
Dynamic: home-page
Dynamic: license
Dynamic: license-file
Dynamic: requires-dist
Dynamic: requires-python
Dynamic: summary
